master/__init__.py
master/besocurl.py
besocurl-0.0.4.dist-info/LICENSE
besocurl-0.0.4.dist-info/METADATA
besocurl-0.0.4.dist-info/WHEEL
besocurl-0.0.4.dist-info/top_level.txt
besocurl-0.0.4.dist-info/RECORD
