Metadata-Version: 2.1
Name: besocurl
Version: 0.0.4
Summary: A library wrapper for PyCurl combained with WinAPI calls to support automatic proxy detection with a 'requests'-like infterface
Home-page: https://github.com/OmriBaso/besocurl
Author: Omri Baso
Author-email: omribaso6@gmail.com
License: UNKNOWN
Platform: UNKNOWN
Classifier: Programming Language :: Python :: 3
Classifier: License :: OSI Approved :: MIT License
Classifier: Operating System :: OS Independent
Requires-Python: >=2.7
